delinea/__init__.py
delinea/secrets/__init__.py
delinea/secrets/server.py
python_tss_sdk-2.0.1.dist-info/licenses/LICENSE
python_tss_sdk-2.0.1.dist-info/WHEEL
python_tss_sdk-2.0.1.dist-info/METADATA
python_tss_sdk-2.0.1.dist-info/RECORD
