Metadata-Version: 2.4
Name: python-tss-sdk
Version: 2.0.1
Summary: The Delinea Secret Server Python SDK
Author: Delinea Integrations
Author-email: GitHub@delinea.com
Requires-Python: >=3.8
Classifier: License :: OSI Approved :: Apache Software License
Classifier: Operating System :: OS Independent
Classifier: Programming Language :: Python :: 3.8
Classifier: Programming Language :: Python :: 3.9
Classifier: Programming Language :: Python :: 3.10
Classifier: Programming Language :: Python :: 3.11
License-File: LICENSE
Requires-Dist: requests >= 2.12.5
